xp3_tool/__init__.py
xp3_tool/xp3_tool.py
xp3_tool-5.1.dist-info/METADATA
xp3_tool-5.1.dist-info/WHEEL
xp3_tool-5.1.dist-info/top_level.txt
xp3_tool-5.1.dist-info/RECORD
