Metadata-Version: 2.1
Name: xp3_tool
Version: 5.1
Summary: xp_t3_tool
Home-page: 
Author: XuPeng
Author-email: xupeng23456@126.com
License: MIT
Classifier: License :: OSI Approved :: MIT License
Classifier: Programming Language :: Python
Classifier: Programming Language :: Python :: 3
Classifier: Programming Language :: Python :: 3.6
Classifier: Programming Language :: Python :: Implementation :: CPython
Classifier: Programming Language :: Python :: Implementation :: PyPy
Requires-Python: >=3.10.0
Requires-Dist: openai
Requires-Dist: pandas
Requires-Dist: oss2
Requires-Dist: python-dotenv
